etc/flowd/flowd.cfg
scitags/__init__.py
scitags/config.py
scitags/service.py
scitags/settings.py
scitags/backends/__init__.py
scitags/backends/dummy.py
scitags/backends/ebpf.py
scitags/backends/prometheus.py
scitags/backends/udp_firefly.py
scitags/netlink/__init__.py
scitags/netlink/cache.py
scitags/netlink/cache_ss.py
scitags/netlink/pyroute_tcp.py
scitags/plugins/__init__.py
scitags/plugins/firefly.py
scitags/plugins/iperf.py
scitags/plugins/iperf_rr.py
scitags/plugins/netlink.py
scitags/plugins/netstat.py
scitags/plugins/np_api.py
scitags/stun/__init__.py
scitags/stun/services.py
scitags-1.1.7.dist-info/licenses/LICENSE
usr/lib/systemd/system/flowd.service
usr/sbin/flowd
scitags-1.1.7.dist-info/METADATA
scitags-1.1.7.dist-info/WHEEL
scitags-1.1.7.dist-info/top_level.txt
scitags-1.1.7.dist-info/RECORD
